eval_metrics/__init__.py
eval_metrics-0.0.1.dist-info/METADATA
eval_metrics-0.0.1.dist-info/WHEEL
eval_metrics-0.0.1.dist-info/top_level.txt
eval_metrics-0.0.1.dist-info/RECORD
